help/__init__.py
rayvision_houdini/__init__.py
rayvision_houdini/analyze_houdini.py
rayvision_houdini/constants.py
rayvision_houdini/run.py
rayvision_houdini/hanalyse/__init__.py
rayvision_houdini/hanalyse/py27/__init__.py
rayvision_houdini/hanalyse/py27/hanalyse.pyd
rayvision_houdini/hanalyse/py27/hanalyse.so
rayvision_houdini/hanalyse/py310/__init__.py
rayvision_houdini/hanalyse/py310/hanalyse.pyd
rayvision_houdini/hanalyse/py310/hanalyse.so
rayvision_houdini/hanalyse/py311/__init__.py
rayvision_houdini/hanalyse/py311/hanalyse.pyd
rayvision_houdini/hanalyse/py311/hanalyse.so
rayvision_houdini/hanalyse/py37/__init__.py
rayvision_houdini/hanalyse/py37/hanalyse.pyd
rayvision_houdini/hanalyse/py37/hanalyse.so
rayvision_houdini/hanalyse/py39/__init__.py
rayvision_houdini/hanalyse/py39/hanalyse.pyd
rayvision_houdini/hanalyse/py39/hanalyse.so
rayvision_houdini/tests/__init__.py
rayvision_houdini/tests/conftest.py
rayvision_houdini/tests/test_analyze_houdini.py
rayvision_houdini-1.5.8.dist-info/METADATA
rayvision_houdini-1.5.8.dist-info/WHEEL
rayvision_houdini-1.5.8.dist-info/top_level.txt
rayvision_houdini-1.5.8.dist-info/RECORD
